mike/__init__.py
mike/app_version.py
mike/arguments.py
mike/commands.py
mike/driver.py
mike/git_utils.py
mike/jsonpath.py
mike/mkdocs.py
mike/mkdocs_plugin.py
mike/mkdocs_utils.py
mike/server.py
mike/versions.py
mike/templates/__init__.py
mike/templates/index.html
mike/templates/redirect.html
mike/themes/__init__.py
mike/themes/material/__init__.py
mike/themes/material/css/version-select.css
mike/themes/material/js/version-select.js
mike/themes/mkdocs/__init__.py
mike/themes/mkdocs/css/version-select.css
mike/themes/mkdocs/js/version-select.js
mike/themes/readthedocs/__init__.py
mike/themes/readthedocs/css/version-select.css
mike/themes/readthedocs/js/version-select.js
mike-2.1.3.dist-info/LICENSE
mike-2.1.3.dist-info/METADATA
mike-2.1.3.dist-info/WHEEL
mike-2.1.3.dist-info/entry_points.txt
mike-2.1.3.dist-info/top_level.txt
mike-2.1.3.dist-info/RECORD
