Metadata-Version: 2.1
Name: mike
Version: 2.1.3
Summary: Manage multiple versions of your MkDocs-powered documentation
Home-page: https://github.com/jimporter/mike
Author: Jim Porter
Author-email: itsjimporter@gmail.com
License: BSD-3-Clause
Keywords: mkdocs multiple versions
Platform: UNKNOWN
Classifier: Development Status :: 5 - Production/Stable
Classifier: Intended Audience :: Developers
Classifier: Topic :: Documentation
Classifier: License :: OSI Approved :: BSD License
Classifier: Programming Language :: Python :: 3
Classifier: Programming Language :: Python :: 3.6
Classifier: Programming Language :: Python :: 3.7
Classifier: Programming Language :: Python :: 3.8
Classifier: Programming Language :: Python :: 3.9
Classifier: Programming Language :: Python :: 3.10
Classifier: Programming Language :: Python :: 3.11
Provides-Extra: dev
Provides-Extra: test
